coordinator/__init__.py
coordinator/py.typed
babichjacob_coordinator-0.1.1.dist-info/METADATA
babichjacob_coordinator-0.1.1.dist-info/WHEEL
babichjacob_coordinator-0.1.1.dist-info/RECORD
