Metadata-Version: 2.1
Name: babichjacob-coordinator
Version: 0.1.1
Summary: A tool for coordinating producers and consumers of data
Home-page: https://github.com/babichjacob/python-coordinator
License: MIT
Author: J or Jacob Babich
Author-email: jacobbabichpublic+git@gmail.com
Requires-Python: >=3.5,<4.0
Classifier: License :: OSI Approved :: MIT License
Classifier: Programming Language :: Python :: 3
Classifier: Programming Language :: Python :: 3.5
Classifier: Programming Language :: Python :: 3.6
Classifier: Programming Language :: Python :: 3.7
Classifier: Programming Language :: Python :: 3.8
Classifier: Programming Language :: Python :: 3.9
Classifier: Programming Language :: Python :: 3.10
Classifier: Programming Language :: Python :: 3.11
Requires-Dist: babichjacob-option-and-result (>=0.2.3,<0.3.0)
Project-URL: Repository, https://github.com/babichjacob/python-coordinator
